{
  "$schema": "https://developer.microsoft.com/json-schemas/fabric/item/report/definition/visualContainer/2.7.0/schema.json",
  "name": "49f36a1c-a55a-45e3-8ad8-27ad965c4455",
  "position": {
    "x": 228.35579514824798,
    "y": 0,
    "z": 2000,
    "height": 93.913043478260875,
    "width": 98.975741239892173,
    "tabOrder": 2000
  },
  "visual": {
    "visualType": "slicer",
    "query": {
      "queryState": {
        "Values": {
          "projections": [
            {
              "field": {
                "Column": {
                  "Expression": {
                    "SourceRef": {
                      "Entity": "dim_dealer"
                    }
                  },
                  "Property": "region"
                }
              },
              "queryRef": "dim_dealer.region",
              "active": true
            }
          ]
        }
      }
    },
    "objects": {
      "data": [
        {
          "properties": {
            "mode": {
              "expr": {
                "Literal": {
                  "Value": "'Basic'"
                }
              }
            }
          }
        }
      ],
      "general": [
        {
          "properties": {}
        }
      ]
    },
    "syncGroup": {
      "groupName": "region",
      "fieldChanges": true,
      "filterChanges": true
    }
  }
}